{
    "official": [
      {
        "id": "community.hq_icons",
        "name": "HQ Icons",
        "author": "ixray-community",
        "category": "Interface",
        "pageUrl": "https://github.com/ixray-community/ixray-hq-icons",
        "status": "verified",
        "supportedGameIds": ["cop"],
        "engineSupport": {
          "min": "r1.3.4",
          "max": ""
        },
        "versions": [
          {
            "version": "2.0",
            "engineSupport": {
              "min": "r1.3.4",
              "max": ""
            },
            "platforms": [
              {
                "gameId": "cop",
                "dependencies": [],
                "sources": [
                  {
                    "url": "https://codeload.github.com/ixray-community/ixray-hq-icons/zip/refs/tags/v2.0",
                    "sha256": "",
                    "mirrors": [
                      {
                        "url": "https://github.com/ixray-community/ixray-hq-icons/releases/download/v2.0/ixray-hq-icons-v2.0.zip",
                        "sha256": ""
                      }
                    ]
                  }
                ]
              }
            ]
          }
        ]
      },
      {
        "id": "community.hd_hud",
        "name": "HD HUD",
        "author": "ixray-community",
        "category": "verified",
        "pageUrl": "https://github.com/ixray-community/ixray-hd-hud",
        "status": "unverified",
        "supportedGameIds": ["cop"],
        "engineSupport": {
          "min": "r1.3",
          "max": ""
        },
        "versions": [
          {
            "version": "1.1",
            "engineSupport": {
              "min": "r1.3",
              "max": ""
            },
            "platforms": [
              {
                "gameId": "cop",
                "dependencies": [],
                "sources": [
                  {
                    "url": "https://codeload.github.com/ixray-community/ixray-hd-hud/zip/refs/tags/v1.1",
                    "sha256": "",
                    "mirrors": [
                      {
                        "url": "https://github.com/ixray-community/ixray-hd-hud/releases/download/v1.1/ixray-hd-hud-v1.1.zip",
                        "sha256": ""
                      }
                    ]
                  }
                ]
              }
            ]
          }
        ]
      },
      {
        "id": "community.st-cop-3.7",
        "name": "ixray-stcop-wp",
        "author": "ixray-community",
        "category": "Guns",
        "pageUrl": "https://github.com/ixray-community/ixray-stcop-wp",
        "status": "unverified",
        "supportedGameIds": ["cop"],
        "engineSupport": {
          "min": "r1.3",
          "max": ""
        },
        "versions": [
          {
            "version": "1.0",
            "engineSupport": {
              "min": "r1.3",
              "max": ""
            },
            "platforms": [
              {
                "gameId": "cop",
                "dependencies": [],
                "sources": [
                  {
                    "url": "https://codeload.github.com/ixray-community/ixray-stcop-wp/zip/refs/tags/v1.0",
                    "sha256": "",
                    "mirrors": [
                      {
                        "url": "https://github.com/ixray-community/ixray-stcop-wp/releases/download/r1.0/ixray-stcop-wp-v3.7-r1.0.7z",
                        "sha256": ""
                      }
                    ]
                  }
                ]
              }
            ]
          }
        ]
      },
      {
        "id": "community.ixray-legs-addon",
        "name": "ixray-legs-addon",
        "author": "ixray-community",
        "category": "Huy znaet",
        "pageUrl": "https://github.com/ixray-community/ixray-legs-addon",
        "status": "unverified",
        "supportedGameIds": ["cop"],
        "engineSupport": {
          "min": "r1.3.4",
          "max": ""
        },
        "versions": [
          {
            "version": "1.1",
            "engineSupport": {
              "min": "r1.3",
              "max": ""
            },
            "platforms": [
              {
                "gameId": "cop",
                "dependencies": [],
                "sources": [
                  {
                    "url": "https://codeload.github.com/ixray-community/ixray-legs-addon/zip/refs/tags/v1.1",
                    "sha256": "",
                    "mirrors": [
                      {
                        "url": "https://github.com/ixray-community/ixray-legs-addon/releases/download/v1.1/ixray-legs-addon-v1.1.zip",
                        "sha256": ""
                      }
                    ]
                  }
                ]
              }
            ]
          }
        ]
      },
      {
        "id": "community.ixray-fixed-weapons",
        "name": "ixray-fixed-weapons",
        "author": "ixray-community",
        "category": "Guns",
        "pageUrl": "https://github.com/ixray-community/ixray-fixed-weapons",
        "status": "unverified",
        "supportedGameIds": ["cop"],
        "engineSupport": {
          "min": "r1.3",
          "max": ""
        },
        "versions": [
          {
            "version": "2.1",
            "engineSupport": {
              "min": "r1.3",
              "max": ""
            },
            "platforms": [
              {
                "gameId": "cop",
                "dependencies": [],
                "sources": [
                  {
                    "url": "https://codeload.github.com/ixray-community/ixray-fixed-weapons/zip/refs/tags/v2.1",
                    "sha256": "",
                    "mirrors": [
                      {
                        "url": "https://github.com/ixray-community/ixray-fixed-weapons/releases/download/v2.1/ixray-fixed-weapons-v2.1.zip",
                        "sha256": ""
                      }
                    ]
                  }
                ]
              }
            ]
          }
        ]
      },
      {
        "id": "community.ixray-paradox-weather-unit",
        "name": "ixray-paradox-weather-unit",
        "author": "ixray-community",
        "category": "Weather",
        "pageUrl": "https://github.com/ixray-community/ixray-paradox-weather-unit",
        "status": "unverified",
        "supportedGameIds": ["cop"],
        "engineSupport": {
          "min": "r1.3",
          "max": ""
        },
        "versions": [
          {
            "version": "2.3",
            "engineSupport": {
              "min": "r1.3",
              "max": ""
            },
            "platforms": [
              {
                "gameId": "cop",
                "dependencies": [],
                "sources": [
                  {
                    "url": "https://codeload.github.com/ixray-community/ixray-paradox-weather-unit/zip/refs/tags/v2.3",
                    "sha256": "",
                    "mirrors": [
                      {
                        "url": "https://github.com/ixray-community/ixray-paradox-weather-unit/releases/download/v2.3/ixray-paradox-weather-unit-v2.3.zip",
                        "sha256": ""
                      }
                    ]
                  }
                ]
              }
            ]
          }
        ],
        "conflicts": [
          "community.ixray-cgim2",
          "community.ixray-atmosfear-3",
          "community.ixray-swtc"
        ]
      },
      {
        "id": "community.ixray-cgim2",
        "name": "ixray-cgim2",
        "author": "ixray-community",
        "category": "Weather",
        "pageUrl": "https://github.com/ixray-community/ixray-cgim2",
        "status": "unverified",
        "supportedGameIds": ["cop"],
        "engineSupport": {
          "min": "r1.3",
          "max": ""
        },
        "versions": [
          {
            "version": "1.0",
            "engineSupport": {
              "min": "r1.3",
              "max": ""
            },
            "platforms": [
              {
                "gameId": "cop",
                "dependencies": [],
                "sources": [
                  {
                    "url": "https://codeload.github.com/ixray-community/ixray-cgim2/zip/refs/tags/v1.0",
                    "sha256": "",
                    "mirrors": [
                      {
                        "url": "https://github.com/ixray-community/ixray-cgim2/releases/download/r1.0/ixray-cgim-r1.0.zip",
                        "sha256": ""
                      }
                    ]
                  }
                ]
              }
            ]
          }
        ]
      },
      {
        "id": "community.ixray-swtc",
        "name": "ixray-swtc",
        "author": "ixray-community",
        "category": "Weather",
        "pageUrl": "https://github.com/ixray-community/ixray-swtc",
        "status": "unverified",
        "supportedGameIds": ["cop"],
        "engineSupport": {
          "min": "r1.3",
          "max": ""
        },
        "versions": [
          {
            "version": "1.0",
            "engineSupport": {
              "min": "r1.3",
              "max": ""
            },
            "platforms": [
              {
                "gameId": "cop",
                "dependencies": [],
                "sources": [
                  {
                    "url": "https://codeload.github.com/ixray-community/ixray-swtc/zip/refs/tags/v1.0",
                    "sha256": "",
                    "mirrors": [
                      {
                        "url": "https://github.com/ixray-community/ixray-swtc/releases/download/r1.0/ixray-swtc-r1.0.zip",
                        "sha256": ""
                      }
                    ]
                  }
                ]
              }
            ]
          }
        ]
      },
      { 
        "id": "community.ixray-atmosfear-3",
        "name": "ixray-atmosfear-3",
        "author": "ixray-community",
        "category": "Weather",
        "pageUrl": "https://github.com/ixray-community/ixray-atmosfear-3",
        "status": "unverified",
        "supportedGameIds": ["cop"],
        "engineSupport": {
          "min": "r1.3",
          "max": ""
        },
        "versions": [
          {
            "version": "1.0",
            "engineSupport": {
              "min": "r1.3",
              "max": ""
            },
            "platforms": [
              {
                "gameId": "cop",
                "dependencies": [],
                "sources": [
                  {
                    "url": "https://codeload.github.com/ixray-community/ixray-atmosfear-3/zip/refs/tags/v1.0",
                    "sha256": "",
                    "mirrors": [
                      {
                        "url": "https://github.com/ixray-community/ixray-atmosfear-3/releases/download/r1.0/ixray-atmosfear-3-r1.0.zip",
                        "sha256": ""
                      }
                    ]
                  }
                ]
              }
            ]
          }
        ]
      },
      { 
        "id": "community.ixray-puddles",
        "name": "ixray-puddles",
        "author": "ixray-community",
        "category": "Weather",
        "pageUrl": "https://github.com/ixray-community/ixray-puddles",
        "status": "unverified",
        "supportedGameIds": ["cop"],
        "engineSupport": {
          "min": "r1.1",
          "max": ""
        },
        "versions": [
          {
            "version": "2.1",
            "engineSupport": {
              "min": "r1.1",
              "max": ""
            },
            "platforms": [
              {
                "gameId": "cop",
                "dependencies": [],
                "sources": [
                  {
                    "url": "https://codeload.github.com/ixray-community/ixray-puddles/zip/refs/tags/v2.1",
                    "sha256": "",
                    "mirrors": [
                      {
                        "url": "https://github.com/ixray-community/ixray-puddles/releases/download/r2.1/ixray-puddles-r2.1.zip",
                        "sha256": ""
                      }
                    ]
                  }
                ]
              }
            ]
          }
        ]
      },
      { 
        "id": "community.ixray-smooth-fade",
        "name": "ixray-smooth-fade",
        "author": "ixray-community",
        "category": "Game",
        "pageUrl": "https://github.com/ixray-community/ixray-smooth-fade",
        "status": "unverified",
        "supportedGameIds": ["cop"],
        "engineSupport": {
          "min": "r1.0",
          "max": ""
        },
        "versions": [
          {
            "version": "1.0",
            "engineSupport": {
              "min": "r1.0",
              "max": ""
            },
            "platforms": [
              {
                "gameId": "cop",
                "dependencies": [],
                "sources": [
                  {
                    "url": "https://codeload.github.com/ixray-community/ixray-smooth-fade/zip/refs/tags/v1.0",
                    "sha256": "",
                    "mirrors": [
                      {
                        "url": "https://github.com/ixray-community/ixray-smooth-fade/releases/download/r1.0/ixray-smooth-fade-r1.0.zip",
                        "sha256": ""
                      }
                    ]
                  }
                ]
              }
            ]
          }
        ]
      }
    ],
    "community": []
  }
